unionai/__init__.py
unionai/actor.py
unionai/artifacts.py
unionai/configuration.py
unionai/filesystems.py
unionai/remote.py
unionai/ucimage.py
unionai-0.1.194.dist-info/licenses/LICENSE
unionai-0.1.194.dist-info/licenses/licenses/APL.txt
unionai-0.1.194.dist-info/licenses/licenses/BSL.txt
unionai-0.1.194.dist-info/METADATA
unionai-0.1.194.dist-info/WHEEL
unionai-0.1.194.dist-info/entry_points.txt
unionai-0.1.194.dist-info/top_level.txt
unionai-0.1.194.dist-info/RECORD
