Metadata-Version: 2.4
Name: unionai
Version: 0.1.194
Summary: Adds Union specific functionality to Flytekit
Author-email: unionai <info@union.ai>
License: Source code in this repository is licensed under the Business Source
Project-URL: Homepage, https://www.union.ai/
Classifier: Intended Audience :: Science/Research
Classifier: Intended Audience :: Developers
Classifier: License :: Other/Proprietary License
Classifier: Programming Language :: Python :: 3.9
Classifier: Programming Language :: Python :: 3.10
Classifier: Programming Language :: Python :: 3.11
Classifier: Programming Language :: Python :: 3.12
Classifier: Topic :: Scientific/Engineering
Classifier: Topic :: Scientific/Engineering :: Artificial Intelligence
Classifier: Topic :: Software Development
Classifier: Topic :: Software Development :: Libraries
Classifier: Topic :: Software Development :: Libraries :: Python Modules
Requires-Python: >=3.9
License-File: licenses/APL.txt
License-File: licenses/BSL.txt
License-File: LICENSE
Requires-Dist: union==0.1.194
Provides-Extra: byoc
Requires-Dist: unionmeta-byoc; extra == "byoc"
Dynamic: license-file
